Workbook
Name A: yearsales!$A$1
Name b: yearsales!$B$1
Name sale: yearsales!$B:$B

Sheet Sheet1
A1: Column1 | B1: Column2 | C1: Column3 | D1: Column32 | E1: Column4 | F1: Column5 | G1: Column6 | H1: Column7 | I1: Column8 | J1: Column9 | K1: Column10 | L1: Column11 | M1: Column12 | N1: Column13
A2: Suppose Discount:0.05 | B2: 0.05 | C2: Releative cell ref. | I2: Absolute Ref. | K2: total discount ke baad like sales-discountprice
A3: Unit_price | B3: Units | C3: Totak_sales | I3: Discount price | J3: sales_discount | K3: Net_Revenue
A4: 10000 | B4: 1 | C4: =1000*1 -> 1000 | E4: formula | G4: sum-sales | H4: =C4+C5+C6+C7 -> 13100 | I4: =C4*$B$2 -> 50 | J4: =C4-I4 -> 950 | K4: =C4-I4 -> 950
A5: 1200 | B5: 3 | C5: =PRODUCT(A5,B5) -> 3600 | E5: function | G5: count_sales | H5: 4 | I5: =C5*$B$2 -> 180 | J5: =C5-I5 -> 3420 | K5: =C5-I5 -> 3420
A6: 1500 | B6: 2 | C6: =PRODUCT(A6,B6) -> 3000 | E6: Trace precedent, it works on function | I6: =C6*$B$2 -> 150 | J6: =C6-I6 -> 2850 | K6: =C6-I6 -> 2850
A7: 1100 | B7: 5 | C7: =PRODUCT(A7,B7) -> 5500 | I7: =C7*$B$2 -> 275 | J7: =C7-I7 -> 5225 | K7: =C7-I7 -> 5225
C8: =AVERAGE(C4:C7) -> 3275 | K8: =AVERAGE(K4:K7) -> 3111.25
C9: here unit_prive into prive
E10: $ sine for fixed column & rows too like c$ means column fixed and like $c$1 means $1 means row fixed
E11: to column add we do insert cell
A12: suppose | B12: 0.5 & 50%
B13: 0.5 | F13: Mixed cell Ref. in here use relative nad absolute | L13: 10 | M13: 20 | N13: Cell ki lication bhi same hona usse fixed karna $ se like i$ for absolute and j$ for fix the location value
A14: Sales | B14: Units | C14: Totak_sales | E14: sales | G14: 10 | H14: 20 | K14: 2 | L14: =K14*L13 -> 20 | M14: =$K14*M$13 -> 40
A15: 10000 | B15: 1 | C15: =1000*1 -> 1000 | F15: 2 | G15: =F$15*G14 -> 20 | H15: =F$15*$H14 -> 40 | K15: 4 | L15: =$K15*L$13 -> 40 | M15: =$K15*M$13 -> 80
A16: 1200 | B16: 3 | C16: =PRODUCT(A16,B16) -> 3600 | F16: 4 | G16: =F$15*G15 -> 40 | H16: =F$15*$H15 -> 80
A17: 1500 | B17: 2 | C17: =PRODUCT(A17,B17) -> 3000
A18: 1100 | B18: 5 | C18: =PRODUCT(A18,B18) -> 5500 | G18: 10 | H18: 20 | I18: 30 | K18: 40
F19: 3 | G19: =$F19*G$18 -> 30 | H19: =$F19*H$18 -> 60 | I19: =$F19*I$18 -> 90 | K19: =$F19*K$18 -> 120
F20: 4 | G20: =$F20*G$18 -> 40 | H20: =$F20*H$18 -> 80 | I20: =$F20*I$18 -> 120 | K20: =$F20*K$18 -> 160
F21: 5 | G21: =$F21*G$18 -> 50 | H21: =$F21*H$18 -> 100 | I21: =$F21*I$18 -> 150 | K21: =$F21*K$18 -> 200
A23: 1

Sheet yearsales
A1: Sales | B1: Units | C1: Totak_sales
A2: 10000 | B2: 1 | C2: =1000*1 -> 1000
A3: 1200 | B3: 3 | C3: =PRODUCT(A3,B3) -> 3600
A4: 1500 | B4: 2 | C4: =PRODUCT(A4,B4) -> 3000
A5: 1100 | B5: 5 | C5: =PRODUCT(A5,B5) -> 5500
A9: Name Range
A10: Agrigate function
B12: JAN | C12: FEB | D12: MAR | E12: APR
A13: Person A | B13: 42 | C13: 10 | D13: 30 | E13: 18 | F13: entry
A14: Person B | B14: 44 | C14: 47 | D14: 50 | E14: 27 | F14: tehsin'
A15: Person C | B15: 22 | C15: 21 | D15: 22 | E15: 49
A16: Person D | B16: 12 | C16: 49 | D16: 25 | E16: 44
A17: Person E | B17: 33 | C17: 28 | D17: 15 | E17: 17
A21: Data conceledation
A22: shift+prss

Sheet 2023
A1: sum of sales | K1: JAN | L1: FEB | M1: MAR | N1: APR
A2: =yearsales!A13 -> Person A | B2: =yearsales!B12 -> JAN | C2: =yearsales!C12 -> FEB | D2: =yearsales!D12 -> MAR | E2: =yearsales!E12 -> APR | J2: Person B | K2: 52.666667 | L2: 102.33333 | M2: 66 | N2: 41.333333
A3: =yearsales!A14 -> Person B | B3: 26 | C3: 69 | D3: 58 | E3: 32 | J3: Person C | K3: 100 | L3: 109.33333 | M3: 37.666667 | N3: 55.666667
A4: =yearsales!A15 -> Person C | B4: 80 | C4: 100 | D4: 24 | E4: 28 | J4: Person D | K4: 78.666667 | L4: 49.666667 | M4: 66.666667 | N4: 90
A5: =yearsales!A16 -> Person D | B5: 60 | C5: 28 | D5: 41 | E5: 83 | J5: Person E | K5: 56 | L5: 65 | M5: 77 | N5: 21
A6: =yearsales!A17 -> Person E | B6: 56 | C6: 65 | D6: 77 | E6: 21
D10: =SUM(sale) -> 164

Sheet 2024
A1: ='2023'!A2 -> Person A | B1: ='2023'!B2 -> JAN | C1: ='2023'!C2 -> FEB | D1: ='2023'!D2 -> MAR | E1: ='2023'!E2 -> APR
A2: ='2023'!A3 -> Person B | B2: =SUM('2023'!B3 '2023'!B3:E6) -> 26 | C2: =SUM('2023'!C3 '2023'!C3:F6) -> 69 | D2: =SUM('2023'!D3 '2023'!D3:G6) -> 58 | E2: =SUM('2023'!E3 '2023'!E3:H6) -> 32
A3: ='2023'!A4 -> Person C | B3: =SUM('2023'!B4 '2023'!B4:E7) -> 80 | C3: =SUM('2023'!C4 '2023'!C4:F7) -> 100 | D3: =SUM('2023'!D4 '2023'!D4:G7) -> 24 | E3: =SUM('2023'!E4 '2023'!E4:H7) -> 28
A4: ='2023'!A5 -> Person D | B4: =SUM('2023'!B5 '2023'!B5:E8) -> 60 | C4: =SUM('2023'!C5 '2023'!C5:F8) -> 28 | D4: =SUM('2023'!D5 '2023'!D5:G8) -> 41 | E4: =SUM('2023'!E5 '2023'!E5:H8) -> 83
A5: ='2023'!A6 -> Person E | B5: =SUM('2023'!B6 '2023'!B6:E9) -> 56 | C5: =SUM('2023'!C6 '2023'!C6:F9) -> 65 | D5: =SUM('2023'!D6 '2023'!D6:G9) -> 77 | E5: =SUM('2023'!E6 '2023'!E6:H9) -> 21

Sheet 2025
A2: ='2023'!A2 -> Person A | B2: ='2023'!B2 -> JAN | C2: ='2023'!C2 -> FEB | D2: ='2023'!D2 -> MAR | E2: ='2023'!E2 -> APR
A3: ='2023'!A3 -> Person B | B3: =SUM('2023:2024'!B3) -> 106 | C3: =SUM('2023:2024'!C3) -> 169 | D3: =SUM('2023:2024'!D3) -> 82 | E3: =SUM('2023:2024'!E3) -> 60
A4: ='2023'!A4 -> Person C | B4: =SUM('2023:2024'!B4) -> 140 | C4: =SUM('2023:2024'!C4) -> 128 | D4: =SUM('2023:2024'!D4) -> 65 | E4: =SUM('2023:2024'!E4) -> 111
A5: ='2023'!A5 -> Person D | B5: =SUM('2023:2024'!B5) -> 116 | C5: =SUM('2023:2024'!C5) -> 93 | D5: =SUM('2023:2024'!D5) -> 118 | E5: =SUM('2023:2024'!E5) -> 104
A6: ='2023'!A6 -> Person E | B6: =SUM('2023:2024'!B6) -> 56 | C6: =SUM('2023:2024'!C6) -> 65 | D6: =SUM('2023:2024'!D6) -> 77 | E6: =SUM('2023:2024'!E6) -> 21
C11: =SUM('2023:2025'!B3) -> 212
C12: =SUM('2023:2025'!B4) -> 280
C13: =SUM('2023:2025'!B5) -> 232
C14: =SUM('2023:2025'!B6) -> 112
C15: =SUM('2023:2025'!B7) -> 0
